kallisticore/__init__.py
kallisticore/apps.py
kallisticore/authentication.py
kallisticore/exceptions.py
kallisticore/permissions.py
kallisticore/renderers.py
kallisticore/serializers.py
kallisticore/signals.py
kallisticore/tasks.py
kallisticore/urls.py
kallisticore/version.py
kallisticore/lib/__init__.py
kallisticore/lib/action.py
kallisticore/lib/credential.py
kallisticore/lib/expectation.py
kallisticore/lib/trial_executor.py
kallisticore/lib/trial_log_recorder.py
kallisticore/lib/trial_scheduler.py
kallisticore/lib/authentication/__init__.py
kallisticore/lib/authentication/jwt.py
kallisticore/lib/observe/__init__.py
kallisticore/lib/observe/observer.py
kallisticore/lib/observe/subject.py
kallisticore/migrations/0001_initial.py
kallisticore/migrations/0002_experiment_steps.py
kallisticore/migrations/0003_trial_parameters.py
kallisticore/migrations/0004_auto_20190416_1800.py
kallisticore/migrations/0005_trial_ticket.py
kallisticore/migrations/0006_trial_initiated_by.py
kallisticore/migrations/0007_trial_completed_at.py
kallisticore/migrations/0008_trial_records.py
kallisticore/migrations/0009_trialschedule.py
kallisticore/migrations/0010_auto_20190618_1356.py
kallisticore/migrations/0011_trialschedule_recurrence_left.py
kallisticore/migrations/0012_auto_20190709_1827.py
kallisticore/migrations/0013_notification.py
kallisticore/migrations/0014_notification_seed.py
kallisticore/migrations/0015_auto_20190906_1502.py
kallisticore/migrations/0016_config.py
kallisticore/migrations/0017_config_seed.py
kallisticore/migrations/0018_delete_config.py
kallisticore/migrations/0019_auto_20201230_1554.py
kallisticore/migrations/0020_trial_initiated_from.py
kallisticore/migrations/__init__.py
kallisticore/models/__init__.py
kallisticore/models/base_model.py
kallisticore/models/experiment.py
kallisticore/models/notification.py
kallisticore/models/singleton_manager.py
kallisticore/models/singleton_model.py
kallisticore/models/step.py
kallisticore/models/trial.py
kallisti_core-1.3.7.dist-info/LICENSE
kallisti_core-1.3.7.dist-info/METADATA
kallisti_core-1.3.7.dist-info/WHEEL
kallisti_core-1.3.7.dist-info/top_level.txt
kallisti_core-1.3.7.dist-info/RECORD
